opendigger_pycli/__init__.py
opendigger_pycli/__main__.py
opendigger_pycli/cli/__init__.py
opendigger_pycli/cli/base.py
opendigger_pycli/cli/custom_types.py
opendigger_pycli/cli/env.py
opendigger_pycli/cli/parsers.py
opendigger_pycli/cli/utils.py
opendigger_pycli/cli/commands/___init__.py
opendigger_pycli/cli/commands/config_cmd.py
opendigger_pycli/cli/commands/display_cmd.py
opendigger_pycli/cli/commands/export_cmd.py
opendigger_pycli/cli/tests/__init__.py
opendigger_pycli/cli/tests/test_query.py
opendigger_pycli/cli/tests/test_repo_name_type.py
opendigger_pycli/config/__init__.py
opendigger_pycli/config/config.py
opendigger_pycli/config/default_config.ini
opendigger_pycli/config/utils.py
opendigger_pycli/console/__init__.py
opendigger_pycli/console/print_base_info.py
opendigger_pycli/console/print_indicator.py
opendigger_pycli/console/print_indicator_graph.py
opendigger_pycli/console/print_indicator_json.py
opendigger_pycli/console/print_indicator_table.py
opendigger_pycli/console/utils.py
opendigger_pycli/console/tests/__init__.py
opendigger_pycli/dataloaders/__init__.py
opendigger_pycli/dataloaders/base.py
opendigger_pycli/dataloaders/indices.py
opendigger_pycli/dataloaders/metrics.py
opendigger_pycli/dataloaders/networks.py
opendigger_pycli/dataloaders/utils.py
opendigger_pycli/dataloaders/tests/__init__.py
opendigger_pycli/dataloaders/tests/test_dataloader_proto_check.py
opendigger_pycli/dataloaders/tests/test_indices.py
opendigger_pycli/dataloaders/tests/test_metrics.py
opendigger_pycli/dataloaders/tests/test_networks.py
opendigger_pycli/datatypes/__init__.py
opendigger_pycli/datatypes/config.py
opendigger_pycli/datatypes/dataloader.py
opendigger_pycli/datatypes/query.py
opendigger_pycli/datatypes/indicators/__init__.py
opendigger_pycli/datatypes/indicators/base.py
opendigger_pycli/datatypes/indicators/indices.py
opendigger_pycli/datatypes/indicators/metrics.py
opendigger_pycli/datatypes/indicators/networks.py
opendigger_pycli/datatypes/tests/__init__.py
opendigger_pycli-1.0.3.dist-info/entry_points.txt
opendigger_pycli-1.0.3.dist-info/LICENSE
opendigger_pycli-1.0.3.dist-info/WHEEL
opendigger_pycli-1.0.3.dist-info/METADATA
opendigger_pycli-1.0.3.dist-info/RECORD
